{
  "introOptions": [
    {
      "id": "kurze_begruessung",
      "label": "kurze Begrüßung",
      "text": "Zu Beginn erfolgte eine kurze Begrüßung."
    },
    {
      "id": "begrussung_orientierung",
      "label": "Begrüßung und Orientierung",
      "text": "Zu Beginn erfolgten Begrüßung und kurze Orientierung."
    },
    {
      "id": "befinden_abfragen",
      "label": "Befinden kurz erfasst",
      "text": "Das aktuelle Befinden wurde zu Beginn kurz erfasst."
    },
    {
      "id": "direkter_einstieg",
      "label": "direkter Einstieg",
      "text": "Nach kurzer Begrüßung erfolgte ein direkter Einstieg in das musiktherapeutische Angebot."
    },
    {
      "id": "ruhiger_einstieg",
      "label": "ruhiger Einstieg",
      "text": "Der Einstieg erfolgte ruhig und strukturierend."
    },
    {
      "id": "stabilisierender_einstieg",
      "label": "stabilisierender Einstieg",
      "text": "Zu Beginn wurde ein stabilisierender Rahmen hergestellt."
    },
    {
      "id": "rueckmelderunde",
      "label": "kurze Rückmelderunde",
      "text": "Es erfolgte eine kurze Rückmelderunde zum aktuellen Befinden.",
      "groupOnly": true
    },
    {
      "id": "neue_teilnehmer",
      "label": "neue Teilnehmende vorgestellt",
      "text": "Neue Teilnehmende wurden vorgestellt und in die Gruppe einbezogen.",
      "groupOnly": true
    },
    {
      "id": "ausfuehrlicher_einstieg",
      "label": "ausführlicherer Einstieg",
      "text": "Vorstellung und Orientierung nahmen zu Beginn mehr Raum ein."
    },
    {
      "id": "moderiert_begrenzt",
      "label": "Gespräch moderiert / begrenzt",
      "text": "Die Einstiegsrunde wurde strukturiert und zeitlich begrenzt.",
      "groupOnly": true
    }
  ],
  "methodGroups": [
    {
      "title": "Aktivierung & Körper",
      "items": [
        {
          "id": "bewegung_musik",
          "label": "Bewegung zur Musik",
          "text": "bewegungsorientierte Elemente zur Musik",
          "focus": "Körperwahrnehmung, Regulation und Aktivierung",
          "langText": "Bewegungsbezogene Musikangebote unterstützten Aktivierung, Körperwahrnehmung und Spannungsregulation."
        },
        {
          "id": "atemtechnik",
          "label": "Atemtechnik",
          "text": "atembezogene Übungen",
          "focus": "Atemregulation und Körperwahrnehmung",
          "langText": "Atembezogene Übungen wurden zur Regulation und Körperwahrnehmung eingesetzt."
        },
        {
          "id": "koerperwahrnehmung",
          "label": "Körperwahrnehmung",
          "text": "Elemente der Körperwahrnehmung",
          "focus": "Körperwahrnehmung und Selbstbezug",
          "langText": "Körperwahrnehmende Elemente dienten der Orientierung im eigenen Spannungs- und Aktivierungsniveau."
        },
        {
          "id": "stimmaktivierung",
          "label": "Einsingen / Stimmaktivierung",
          "text": "Stimmaktivierung",
          "focus": "Aktivierung, Selbstwahrnehmung und Ausdrucksförderung",
          "langText": "Stimmliche Angebote dienten der Aktivierung, Selbstwahrnehmung und Ausdrucksförderung."
        }
      ]
    },
    {
      "title": "Rhythmus & Koordination",
      "items": [
        {
          "id": "bodypercussion",
          "label": "Bodypercussion",
          "text": "Bodypercussion",
          "focus": "Rhythmus, Koordination und Aktivierung"
        },
        {
          "id": "rhythmus_instrumente",
          "label": "Rhythmusarbeit mit Instrumenten",
          "text": "Rhythmusarbeit mit Instrumenten",
          "focus": "Strukturierung, Aktivierung und Gruppensynchronisation",
          "singleFocus": "Strukturierung, Aktivierung und Koordination",
          "langText": "Rhythmische Elemente unterstützten Strukturierung, Aktivierung und Gruppensynchronisation.",
          "singleLangText": "Rhythmische Elemente unterstützten Strukturierung, Aktivierung und Koordination."
        },
        {
          "id": "koordination_sync",
          "label": "Koordination / Synchronisation",
          "text": "koordinative und synchronisierende Gruppenübungen",
          "focus": "Koordination, gemeinsamer Puls und Gruppensynchronisation",
          "groupOnly": true
        },
        {
          "id": "taketina",
          "label": "TaKeTiNa-orientierte Rhythmusarbeit",
          "text": "TaKeTiNa-orientierte Rhythmusarbeit",
          "focus": "rhythmische Orientierung, Aufmerksamkeit und Selbstregulation",
          "groupOnly": true
        }
      ]
    },
    {
      "title": "Arbeit mit Liedern",
      "items": [
        {
          "id": "bekanntes_lied",
          "label": "bekanntes Lied gemeinsam singen",
          "text": "gemeinsames Singen eines bekannten Liedes",
          "singleText": "Singen eines bekannten Liedes",
          "focus": "Stimme, Vertrautheit und musikalische Resonanz",
          "langText": "Das Singen eines bekannten Liedes nutzte Vertrautheit, Stimme und musikalische Resonanz als stabilisierende Zugänge."
        },
        {
          "id": "lied_einfuehren",
          "label": "Lied neu vorstellen / einführen",
          "text": "die Einführung eines neuen Liedes",
          "focus": "Orientierung, Stimme und musikalischer Zugang",
          "langText": "Die Einführung eines neuen Liedes erfolgte orientierend und förderte den musikalischen Zugang."
        },
        {
          "id": "lied_impuls",
          "label": "Lied als Impuls",
          "text": "Lied als Impuls",
          "focus": "emotionaler Zugang, Selbstbezug und musikalische Resonanz",
          "langText": "Das Lied wurde als musiktherapeutischer Impuls für emotionalen Zugang und musikalische Resonanz genutzt."
        },
        {
          "id": "lied_elemente",
          "label": "mit Lied-Elementen arbeiten",
          "text": "Arbeit mit einzelnen Elementen eines Liedes",
          "focus": "Text, Melodie, Rhythmus und thematische Vertiefung",
          "langText": "Einzelne Liedelemente wurden zur strukturierten thematischen und musikalischen Vertiefung genutzt."
        }
      ]
    },
    {
      "title": "Improvisation & freies Arbeiten",
      "items": [
        {
          "id": "freie_impro",
          "label": "freie Improvisation",
          "text": "freie Improvisation",
          "focus": "Ausdruck, Spontaneität und musikalisches Gestalten",
          "langText": "Freie Improvisation ermöglichte spontanen musikalischen Ausdruck und eigenes Gestalten."
        },
        {
          "id": "thematische_impro",
          "label": "thematische Improvisation",
          "text": "thematische Improvisation",
          "focus": "nonverbaler Ausdruck, Selbstbezug und inneres Erleben",
          "langText": "Die thematische Improvisation ermöglichte nonverbalen Ausdruck und Selbstbezug."
        },
        {
          "id": "ausdruck",
          "label": "Ausdruck über Stimme / Musik",
          "text": "Ausdrucksarbeit über Stimme und Musik",
          "focus": "Ausdrucksfähigkeit und emotionaler Zugang",
          "langText": "Stimme und Musik wurden als direkte Ausdrucksmedien eingesetzt."
        }
      ]
    },
    {
      "title": "Musik hören & Einordnung",
      "items": [
        {
          "id": "musik_hoeren",
          "label": "gemeinsames Musik hören",
          "text": "gemeinsames Musik hören",
          "singleText": "Musikhören",
          "focus": "Wahrnehmungslenkung, Resonanzbildung und kurze Einordnung",
          "langText": "Das gemeinsame Hören von Musik wurde zur Wahrnehmungslenkung, Resonanzbildung und kurzen Einordnung genutzt.",
          "singleLangText": "Das Musikhören wurde zur Wahrnehmungslenkung, Resonanzbildung und kurzen Einordnung genutzt."
        },
        {
          "id": "biografische_musik",
          "label": "biografische Musikarbeit",
          "text": "biografisch orientierte Musikarbeit",
          "focus": "biografischer Bezug, Selbstbezug und Austausch",
          "singleFocus": "biografischer Bezug und Selbstbezug",
          "langText": "Biografisch orientierte Musikarbeit ermöglichte einen klinisch gut fassbaren Bezug zu vertrauter Musik."
        },
        {
          "id": "austausch_feedback",
          "label": "Austausch / Rückmeldung",
          "text": "Austausch und Rückmeldungen innerhalb der Gruppe",
          "focus": "Kontaktgestaltung, Rückmeldung und soziale Resonanz",
          "groupOnly": true
        }
      ]
    },
    {
      "title": "Interaktion & erfahrungsorientierte Methoden",
      "items": [
        {
          "id": "partnerarbeit",
          "label": "Partnerarbeit (z. B. Live-Kinetik)",
          "text": "Partnerarbeit mit koordinativen Elementen",
          "focus": "Kontakt, Koordination und Abstimmung",
          "langText": "Koordinative Partnerarbeit unterstützte Kontaktaufnahme, Abstimmung und Aufmerksamkeitslenkung."
        },
        {
          "id": "gfk",
          "label": "GFK-Übungen",
          "text": "kommunikations- und wahrnehmungsbezogene Übungen aus der GFK",
          "focus": "Wahrnehmung, Kommunikation und Selbstklärung",
          "langText": "Wahrnehmungs- und kommunikationsbezogene Übungen unterstützten klare Benennung und Abstimmung."
        },
        {
          "id": "begrussungsritual",
          "label": "Begrüßungsrituale",
          "text": "Begrüßungsrituale",
          "focus": "Kontaktaufnahme und Gruppenorientierung",
          "groupOnly": true
        },
        {
          "id": "erfahrungsuebung",
          "label": "angeleitete Erfahrungsübungen",
          "text": "angeleitete erfahrungsorientierte Übungen",
          "focus": "Selbstwahrnehmung, Erfahrung und kurze Einordnung",
          "langText": "Angeleitete Erfahrungsübungen unterstützten Selbstwahrnehmung und eine kurze klinische Einordnung des Erlebten."
        },
        {
          "id": "raumwahrnehmung",
          "label": "Raumwahrnehmung über Bewegung",
          "text": "Raumwahrnehmung über Gehen, Erkunden und Beschreiben",
          "focus": "Raumwahrnehmung, Orientierung und Selbstbezug",
          "langText": "Raumbezogene Bewegung unterstützte Orientierung, Körperwahrnehmung und Aktivierung."
        },
        {
          "id": "geschichten",
          "label": "Geschichten / szenisches Arbeiten",
          "text": "szenische Methoden mit Entwicklung eigener Geschichten",
          "focus": "Kreativität, Ausdruck und Perspektivwechsel",
          "langText": "Szenische Methoden ermöglichten Ausdruck, Perspektivwechsel und strukturierte Gestaltung."
        }
      ]
    },
    {
      "title": "Regulation & Abschluss",
      "items": [
        {
          "id": "entspannung",
          "label": "Entspannung",
          "text": "entspannende Elemente",
          "focus": "Regulation, Entlastung und Beruhigung",
          "langText": "Entspannende Elemente wurden zur Beruhigung und Spannungsregulation eingesetzt."
        },
        {
          "id": "ruhiger_ausklang",
          "label": "ruhiger Ausklang / Summen",
          "text": "ein ruhiger Ausklang mit Summen oder Tönen",
          "focus": "Beruhigung, Stimme und Selbstregulation",
          "langText": "Summen und Tönen unterstützten einen ruhigen Abschluss und die Selbstregulation."
        },
        {
          "id": "abschlusslied",
          "label": "Abschlusslied",
          "text": "ein Abschlusslied",
          "focus": "Rahmung, Orientierung und Abschluss",
          "langText": "Das Abschlusslied diente der Rahmung, Orientierung und klaren Beendigung der Stunde."
        },
        {
          "id": "kurze_reflexion",
          "label": "kurze Einordnung",
          "text": "eine kurze Einordnung zum Abschluss",
          "focus": "kurze Einordnung und Abschluss",
          "langText": "Die kurze Einordnung diente der knappen Abrundung der Stunde."
        }
      ]
    }
  ],
  "selects": {
    "dynamic": [
      [
        "",
        "nicht übernehmen",
        ""
      ],
      [
        "konstant_stabil",
        "konstant stabil",
        "Der Gruppenverlauf blieb konstant stabil."
      ],
      [
        "zunehmend_geoeffnet",
        "zunehmend geöffnet",
        "Die Offenheit innerhalb der Gruppe nahm zu."
      ],
      [
        "zunehmend_unruhig",
        "zunehmend unruhig",
        "Die Unruhe innerhalb der Gruppe nahm zu."
      ],
      [
        "schwankend",
        "schwankend",
        "Der Gruppenverlauf blieb wechselhaft."
      ],
      [
        "schwer_kontakt",
        "schwer in Kontakt kommend",
        "Kontakt innerhalb der Gruppe kam nur erschwert zustande."
      ]
    ],
    "participation": [
      [
        "",
        "nicht übernehmen",
        ""
      ],
      [
        "aktiv",
        "aktiv beteiligt",
        "Die Beteiligung war aktiv."
      ],
      [
        "wechselhaft",
        "wechselhaft beteiligt",
        "Die Beteiligung war wechselhaft."
      ],
      [
        "zurueckhaltend",
        "eher zurückhaltend",
        "Die Beteiligung blieb eher zurückhaltend."
      ],
      [
        "passiv",
        "passiv / beobachtend",
        "Die Beteiligung war überwiegend passiv und beobachtend."
      ]
    ],
    "access": [
      [
        "",
        "nicht übernehmen",
        ""
      ],
      [
        "gut_erreichbar",
        "gut erreichbar",
        "Ein emotionaler Zugang war gut möglich."
      ],
      [
        "vorsichtig",
        "vorsichtig / zurückhaltend",
        "Der emotionale Zugang war vorsichtig und zurückhaltend."
      ],
      [
        "punktuell_geoeffnet",
        "punktuell geöffnet",
        "Ein emotionaler Zugang entstand punktuell."
      ],
      [
        "erschwert",
        "erschwert zugänglich",
        "Der emotionale Zugang war erschwert."
      ],
      [
        "belastet",
        "emotional belastet",
        "Emotional belastete Anteile wurden sichtbar."
      ]
    ],
    "effect": [
      [
        "",
        "nicht übernehmen",
        ""
      ],
      [
        "stabilisierend",
        "stabilisierend",
        "Die Stunde wirkte insgesamt stabilisierend."
      ],
      [
        "aktivierend",
        "aktivierend",
        "Die Stunde wirkte insgesamt aktivierend."
      ],
      [
        "emotional_oeffnend",
        "emotional öffnend",
        "Die Stunde wirkte insgesamt emotional öffnend."
      ],
      [
        "strukturierend",
        "strukturierend",
        "Die Stunde wirkte insgesamt strukturierend."
      ],
      [
        "entlastend",
        "entlastend",
        "Die Stunde wirkte insgesamt entlastend."
      ],
      [
        "anregend",
        "anregend",
        "Die Stunde wirkte insgesamt anregend."
      ]
    ],
    "groupClimate": [
      [
        "",
        "nicht übernehmen",
        ""
      ],
      [
        "tragfaehig",
        "tragfähig",
        "Das Gruppenklima wirkte tragfähig."
      ],
      [
        "vorsichtig",
        "vorsichtig",
        "Das Gruppenklima blieb zunächst vorsichtig."
      ],
      [
        "distanziert",
        "distanziert",
        "Das Gruppenklima wirkte phasenweise distanziert."
      ],
      [
        "angespannt",
        "angespannt",
        "Das Gruppenklima war von Anspannung geprägt."
      ],
      [
        "unterstuetzend",
        "unterstützend",
        "Das Gruppenklima wirkte unterstützend."
      ]
    ],
    "groupDynamics": [
      [
        "",
        "nicht übernehmen",
        ""
      ],
      [
        "kooperativ",
        "kooperativ",
        "Die Gruppendynamik war kooperativ."
      ],
      [
        "wechselhaft",
        "wechselhaft",
        "Die Gruppendynamik verlief wechselhaft."
      ],
      [
        "unruhig",
        "unruhig",
        "Die Gruppendynamik war phasenweise unruhig."
      ],
      [
        "zurueckhaltend",
        "zurückhaltend",
        "Die Gruppendynamik blieb zurückhaltend."
      ],
      [
        "strukturbeduerftig",
        "strukturbedürftig",
        "Die Gruppe benötigte wiederholt Strukturierung."
      ]
    ],
    "groupIntegration": [
      [
        "",
        "nicht übernehmen",
        ""
      ],
      [
        "gut",
        "gut integriert",
        "Einzelne Teilnehmende waren gut eingebunden."
      ],
      [
        "teilweise",
        "teilweise integriert",
        "Einzelne Teilnehmende waren teilweise eingebunden."
      ],
      [
        "randstaendig",
        "einzelne randständig",
        "Einzelne Teilnehmende blieben eher randständig."
      ],
      [
        "unterschiedlich",
        "unterschiedliche Beteiligung",
        "Einbindung und Beteiligung waren innerhalb der Gruppe unterschiedlich ausgeprägt."
      ]
    ],
    "singleContact": [
      [
        "",
        "nicht übernehmen",
        ""
      ],
      [
        "gut",
        "gut kontaktfähig",
        "gut erreichbarer Kontakt"
      ],
      [
        "vorsichtig",
        "vorsichtig / zurückhaltend",
        "vorsichtiger und zurückhaltender Kontakt"
      ],
      [
        "wechselhaft",
        "wechselhaft",
        "wechselhafter Kontakt"
      ],
      [
        "vermeidend",
        "vermeidend",
        "vermeidender Kontakt"
      ],
      [
        "schwer",
        "schwer erreichbar",
        "erschwert erreichbarer Kontakt"
      ]
    ],
    "singleExpression": [
      [
        "",
        "nicht übernehmen",
        ""
      ],
      [
        "aktiv",
        "aktiv eingebracht",
        "bei aktivem Ausdruck"
      ],
      [
        "zoegerlich",
        "zögerlich eingebracht",
        "bei zögerlichem Ausdruck"
      ],
      [
        "beobachtend",
        "überwiegend beobachtend",
        "bei überwiegend beobachtendem Verhalten"
      ],
      [
        "impulsiv",
        "impulsiv / unstrukturiert",
        "bei impulsivem und wenig strukturiertem Ausdruck"
      ],
      [
        "orientiert",
        "angepasst / orientiert",
        "bei angepasstem und orientiertem Verhalten"
      ]
    ],
    "singleAffect": [
      [
        "",
        "nicht übernehmen",
        ""
      ],
      [
        "stabil",
        "stabil",
        "stabil"
      ],
      [
        "angespannt",
        "angespannt",
        "angespannt"
      ],
      [
        "niedergedrueckt",
        "niedergedrückt",
        "niedergedrückt"
      ],
      [
        "labil",
        "labil",
        "emotional labil"
      ],
      [
        "beteiligt",
        "emotional beteiligt",
        "emotional beteiligt"
      ]
    ],
    "singleRegulation": [
      [
        "",
        "nicht übernehmen",
        ""
      ],
      [
        "stabil",
        "stabil",
        "Die Selbstregulation war stabil."
      ],
      [
        "unterstuetzung",
        "unterstützungsbedürftig",
        "Die Selbstregulation war unterstützungsbedürftig."
      ],
      [
        "ueberfordert",
        "überfordert",
        "Die Selbstregulation war bei erhöhter Anforderung überfordert."
      ],
      [
        "zunehmend",
        "zunehmend reguliert",
        "Die Selbstregulation gelang zunehmend besser."
      ],
      [
        "struktur",
        "reagierte auf Struktur",
        "Auf strukturierende Impulse konnte reagiert werden."
      ]
    ],
    "singleResources": [
      [
        "",
        "nicht übernehmen",
        ""
      ],
      [
        "gut",
        "gut zugänglich",
        "Ressourcen waren gut zugänglich."
      ],
      [
        "punktuell",
        "punktuell zugänglich",
        "Ressourcen waren punktuell zugänglich."
      ],
      [
        "erschwert",
        "schwer zugänglich",
        "Der Zugang zu Ressourcen war erschwert."
      ],
      [
        "musik",
        "durch Musik aktiviert",
        "Musikalische Angebote erleichterten den Zugang zu Ressourcen."
      ],
      [
        "kaum",
        "kaum erreichbar",
        "Ressourcen waren kaum erreichbar."
      ]
    ],
    "closing": [
      [
        "",
        "keine Abschlussformulierung",
        ""
      ],
      [
        "keine_auffaelligkeiten",
        "keine besonderen Auffälligkeiten",
        "Es ergaben sich keine besonderen klinischen Auffälligkeiten."
      ],
      [
        "fortfuehrung",
        "Fortführung im Behandlungsplan",
        "Eine Fortführung im Rahmen des Behandlungsplans ist vorgesehen."
      ],
      [
        "beobachtung",
        "weiterer Verlauf wird beobachtet",
        "Der weitere Verlauf wird beobachtet."
      ],
      [
        "anpassung",
        "Anpassung empfohlen",
        "Eine Anpassung des weiteren Vorgehens wird empfohlen."
      ]
    ]
  },
  "singlePhrases": {
    "contact": {
      "gut": "gut erreichbar",
      "vorsichtig": "vorsichtig",
      "wechselhaft": "wechselhaft erreichbar",
      "vermeidend": "eher vermeidend",
      "schwer": "erschwert erreichbar"
    },
    "groupContact": {
      "gut": "gut erreichbar",
      "vorsichtig": "vorsichtig",
      "wechselhaft": "wechselhaft erreichbar",
      "vermeidend": "eher vermeidend",
      "schwer": "erschwert erreichbar"
    },
    "expression": {
      "aktiv": {
        "single": "brachte {pronoun} sich aktiv und gestaltend ein",
        "group": "{subject} war ein aktives und gestaltendes Einbringen beobachtbar."
      },
      "zoegerlich": {
        "single": "blieb der musikalische und verbale Ausdruck zunächst zögerlich",
        "group": "{subject} blieb der musikalische und verbale Ausdruck zunächst zögerlich.",
        "sentence": "Der musikalische und verbale Ausdruck blieb zunächst zögerlich."
      },
      "beobachtend": {
        "single": "nahm {pronoun} überwiegend beobachtend teil",
        "group": "{subject} blieb das Verhalten überwiegend beobachtend."
      },
      "impulsiv": {
        "single": "wirkte der Ausdruck impulsiv und wenig strukturiert",
        "group": "{subject} wirkte der Ausdruck impulsiv und wenig strukturiert."
      },
      "orientiert": {
        "single": "wirkte das Verhalten angepasst und orientiert",
        "group": "{subject} wirkte das Verhalten angepasst und orientiert."
      }
    },
    "affect": {
      "stabil": "stabil",
      "angespannt": "angespannt",
      "niedergedrueckt": "niedergedrückt",
      "labil": "emotional labil",
      "beteiligt": "emotional beteiligt"
    },
    "regulation": {
      "stabil": {
        "single": "{subject} konnte die Selbstregulation stabil halten.",
        "group": "{prefix} blieb die Selbstregulation stabil."
      },
      "unterstuetzung": {
        "single": "{subject} profitierte bei der Selbstregulation von strukturierenden Impulsen.",
        "group": "{prefix} ließ sich die Selbstregulation durch strukturierende Impulse unterstützen."
      },
      "ueberfordert": {
        "single": "{subject} benötigte bei erhöhter Anforderung Unterstützung zur Regulation.",
        "group": "{prefix} war bei erhöhter Anforderung Unterstützung zur Regulation erforderlich."
      },
      "zunehmend": {
        "single": "{subject} gelang die Selbstregulation zunehmend besser.",
        "group": "{prefix} gelang die Selbstregulation zunehmend besser."
      },
      "struktur": {
        "single": "{subject} reagierte zunehmend auf strukturierende musikalische Impulse.",
        "group": "{prefix} war eine zunehmende Reaktion auf strukturierende musikalische Impulse beobachtbar."
      }
    },
    "resources": {
      "gut": {
        "single": "Bei {dative} waren Ressourcen gut zugänglich.",
        "group": "{prefix} waren Ressourcen gut zugänglich."
      },
      "punktuell": {
        "single": "Bei {dative} waren Ressourcen punktuell zugänglich und konnten über musikalische Angebote aktiviert werden.",
        "group": "{prefix} waren Ressourcen punktuell zugänglich und konnten über musikalische Angebote aktiviert werden."
      },
      "erschwert": {
        "single": "Bei {dative} waren Ressourcen nur erschwert zugänglich.",
        "group": "{prefix} waren Ressourcen nur erschwert zugänglich."
      },
      "musik": {
        "single": "Bei {dative} erleichterten musikalische Angebote den Zugang zu Ressourcen.",
        "group": "{prefix} erleichterten musikalische Angebote den Zugang zu Ressourcen."
      },
      "kaum": {
        "single": "Bei {dative} waren Ressourcen kaum zugänglich.",
        "group": "{prefix} waren Ressourcen kaum zugänglich."
      }
    }
  }
}
